{
    "data": [
        {
            "data": {
                "district": "6385008f69df036e83e984a3",
                "principal": {
                    "email": "tdkhan@mailinator.com",
                    "name": "Theodora Khan"
                },
                "sis_id": "02M800",
                "name": "City High School",
                "last_modified": "2022-11-28T18:46:36.278Z",
                "phone": "(212) 555-1212",
                "high_grade": "12",
                "school_number": "02M800",
                "location": {
                    "zip": "10001",
                    "address": "350 5th Avenue",
                    "city": "New York",
                    "state": "NY"
                },
                "low_grade": "9",
                "state_id": "712345",
                "created": "2022-11-28T18:46:36.278Z",
                "id": "63850203bfb8460546071e5e"
            },
            "uri": "/v3.0/schools/63850203bfb8460546071e5e"
        }
    ],
    "links": [
        {
            "rel": "self",
            "uri": "/v3.0/schools?limit=1"
        },
        {
            "rel": "next",
            "uri": "/v3.0/schools?limit=1&starting_after=63850203bfb8460546071e5e"
        }
    ]
}